paytm_api/__init__.py
paytm_api/core.py
pmp_verifier-1.0.0.dist-info/METADATA
pmp_verifier-1.0.0.dist-info/WHEEL
pmp_verifier-1.0.0.dist-info/top_level.txt
pmp_verifier-1.0.0.dist-info/RECORD
