Metadata-Version: 2.4
Name: pmp_verifier
Version: 1.0.0
Summary: Simple Python library to verify Paytm Merchant transaction status
Home-page: https://github.com/DragoServer/paytm_api
Author: DragoServer
Author-email: rahamanmasiur124@gmail.com
License: MIT
Classifier: Programming Language :: Python :: 3
Classifier: License :: OSI Approved :: MIT License
Classifier: Operating System :: OS Independent
Requires-Python: >=3.7
Requires-Dist: requests
